cubewerx/__init__.py
cubewerx/stratos.py
cubewerx_stratos-9.7.11.dist-info/licenses/LICENSE.txt
cubewerx_stratos-9.7.11.dist-info/METADATA
cubewerx_stratos-9.7.11.dist-info/WHEEL
cubewerx_stratos-9.7.11.dist-info/top_level.txt
cubewerx_stratos-9.7.11.dist-info/RECORD
