Metadata-Version: 2.4
Name: cubewerx-stratos
Version: 9.7.11
Summary: The CubeWerx Stratos Administration Interface
Author-email: Keith Pomakis <pomakis@cubewerx.com>
License-Expression: LicenseRef-Proprietary
Project-URL: Homepage, https://www.cubewerx.com/
Classifier: Development Status :: 3 - Alpha
Classifier: Operating System :: OS Independent
Classifier: Programming Language :: Python :: 3.11
Requires-Python: >=3.11
License-File: LICENSE.txt
Requires-Dist: validators
Requires-Dist: requests
Requires-Dist: geojson
Requires-Dist: Pillow
Dynamic: license-file
